{"match_id":"15995","starters":[{"carne":"26931","name":"FEDERICO ROVELLA","shirt":"1","captain":false},{"carne":"22549","name":"PATRICIO MARTIN SARNO","shirt":"2","captain":true},{"carne":"23880","name":"MARTIN WALLERSTEIN","shirt":"3","captain":false},{"carne":"23898","name":"JOSE IGNACIO MARTIN","shirt":"4","captain":false},{"carne":"27195","name":"MATIAS NICOLAS RODRIGUEZ","shirt":"5","captain":false},{"carne":"27068","name":"TOMAS SEBASTIAN CONROY","shirt":"8","captain":false},{"carne":"24038","name":"JUAN PEDRO CALVIÑO","shirt":"9","captain":false},{"carne":"27175","name":"FEDERICO SALHON","shirt":"10","captain":false},{"carne":"26528","name":"MARIO SZLAFMYC","shirt":"11","captain":false},{"carne":"28266","name":"FRANCISCO BLIMAN","shirt":"14","captain":false},{"carne":"27148","name":"NICOLAS GERWER","shirt":"18","captain":false}],"subs":[{"out_carne":"27068","out_name":"TOMAS SEBASTIAN CONROY","in_carne":"25307","in_name":"RAFAEL MARASCIO","shirt":"19","minute":"0"},{"out_carne":"27148","out_name":"NICOLAS GERWER","in_carne":"25925","in_name":"MANUEL MARTIN ASTIGARRAGA","shirt":"7","minute":"0"},{"out_carne":"23898","out_name":"JOSE IGNACIO MARTIN","in_carne":"27148","in_name":"NICOLAS GERWER","shirt":"18","minute":"0"}],"goals":[{"carne":"24038","name":"JUAN PEDRO CALVIÑO","minute":"0","own_goal":false},{"carne":"27175","name":"FEDERICO SALHON","minute":"0","own_goal":false}],"yellows":[],"reds":[]}