{"match_id":"43161","starters":[{"carne":"40246","name":"LUCAS NERY CALCAGNO","shirt":"4","captain":false},{"carne":"39525","name":"MARTIN DONNANGELO","shirt":"11","captain":true},{"carne":"40998","name":"FELIPE FRUGONE","shirt":"15","captain":false},{"carne":"40992","name":"JUAN PEDRO URRESTARAZU","shirt":"19","captain":false},{"carne":"41001","name":"DIEGO DABEZIES","shirt":"29","captain":false},{"carne":"42717","name":"LUCAS ROHR","shirt":"31","captain":false},{"carne":"41009","name":"BRUNO NICOLAS RAVERA","shirt":"41","captain":false},{"carne":"41007","name":"GERARDO SACCO","shirt":"47","captain":false},{"carne":"42265","name":"JUAN IGNACIO FOURMANE","shirt":"50","captain":false},{"carne":"42071","name":"SANTIAGO ALGORTA","shirt":"57","captain":false},{"carne":"43493","name":"FEDERICO HAZAN","shirt":"74","captain":false}],"subs":[{"out_carne":"40992","out_name":"JUAN PEDRO URRESTARAZU","in_carne":"42070","in_name":"FRANCISCO GUADALUPE","shirt":"3","minute":"0"},{"out_carne":"41007","out_name":"GERARDO SACCO","in_carne":"43969","in_name":"MAURO DONNANGELO","shirt":"39","minute":"0"},{"out_carne":"43493","out_name":"FEDERICO HAZAN","in_carne":"43952","in_name":"MARTIN KRUCHINSKI","shirt":"55","minute":"0"}],"goals":[{"carne":"42071","name":"SANTIAGO ALGORTA","minute":"0","own_goal":false}],"yellows":[],"reds":[]}