{"match_id":"44267","starters":[{"carne":"31878","name":"MAXIMILIANO SALA","shirt":"5","captain":false},{"carne":"29072","name":"BRUNO RODRIGUEZ","shirt":"8","captain":true},{"carne":"28619","name":"NICOLAS RODRIGUEZ","shirt":"11","captain":false},{"carne":"39090","name":"PAULUS JAN ELBERSE","shirt":"12","captain":false},{"carne":"29732","name":"FERNANDO ARTOLA","shirt":"14","captain":false},{"carne":"28144","name":"ANDRES ANTONIO BESIO","shirt":"16","captain":false},{"carne":"19944","name":"MAURICIO JAVIER GENINAZZI","shirt":"18","captain":false},{"carne":"29653","name":"MARTIN MUSETTI","shirt":"21","captain":false},{"carne":"35975","name":"RODRIGO SCHRAMM","shirt":"22","captain":false},{"carne":"20439","name":"RODRIGO PABLO BAUBETA","shirt":"25","captain":false},{"carne":"22253","name":"LUCAS MORISIO","shirt":"26","captain":false}],"subs":[{"out_carne":"28619","out_name":"NICOLAS RODRIGUEZ","in_carne":"33856","in_name":"FEDERICO CHIANCONE","shirt":"3","minute":"0"},{"out_carne":"20439","out_name":"RODRIGO PABLO BAUBETA","in_carne":"18137","in_name":"MATIAS VALENTIN ROSENDE","shirt":"4","minute":"0"},{"out_carne":"35975","out_name":"RODRIGO SCHRAMM","in_carne":"26011","in_name":"MAURO GIAMMARCHI","shirt":"7","minute":"0"},{"out_carne":"28144","out_name":"ANDRES ANTONIO BESIO","in_carne":"25925","in_name":"MANUEL MARTIN ASTIGARRAGA","shirt":"30","minute":"0"}],"goals":[{"carne":"29653","name":"MARTIN MUSETTI","minute":"1","own_goal":false}],"yellows":[],"reds":[]}