{"match_id":"60272","starters":[{"carne":"28362","name":"JUAN PABLO MARSICANO","shirt":"1","captain":false},{"carne":"34065","name":"GABRIEL PFEFFER","shirt":"3","captain":false},{"carne":"31878","name":"MAXIMILIANO SALA","shirt":"5","captain":false},{"carne":"28371","name":"MAXIMILIANO JAVIER CRISTIANI","shirt":"6","captain":false},{"carne":"20675","name":"RODRIGO RAUL TURNES","shirt":"10","captain":false},{"carne":"29732","name":"FERNANDO ARTOLA","shirt":"14","captain":false},{"carne":"19944","name":"MAURICIO JAVIER GENINAZZI","shirt":"18","captain":true},{"carne":"43969","name":"MAURO DONNANGELO","shirt":"20","captain":false},{"carne":"29653","name":"MARTIN MUSETTI","shirt":"21","captain":false},{"carne":"31952","name":"JOAQUIN REBELLATO","shirt":"33","captain":false},{"carne":"44291","name":"IGNACIO GEISINGER","shirt":"50","captain":false}],"subs":[{"out_carne":"20675","out_name":"RODRIGO RAUL TURNES","in_carne":"30797","in_name":"SANTIAGO ROSENDE","shirt":"25","minute":"8"},{"out_carne":"28362","out_name":"JUAN PABLO MARSICANO","in_carne":"32517","in_name":"VENANCIO FLORES","shirt":"12","minute":"58"},{"out_carne":"44291","out_name":"IGNACIO GEISINGER","in_carne":"38065","in_name":"JOAQUIN ARRETCHE","shirt":"28","minute":"63"},{"out_carne":"31878","out_name":"MAXIMILIANO SALA","in_carne":"27195","in_name":"MATIAS NICOLAS RODRIGUEZ","shirt":"15","minute":"71"}],"goals":[{"carne":"20675","name":"RODRIGO RAUL TURNES","minute":"63","own_goal":false},{"carne":"28371","name":"MAXIMILIANO JAVIER CRISTIANI","minute":"83","own_goal":false},{"carne":"29653","name":"MARTIN MUSETTI","minute":"85","own_goal":false}],"yellows":[],"reds":[]}