{"match_id":"63247","starters":[{"carne":"46709","name":"AGUSTIN MONTERO","shirt":"2","captain":false},{"carne":"44899","name":"JUAN MARTIN DEFFEMINIS","shirt":"3","captain":false},{"carne":"44918","name":"JOAQUIN BLANCO","shirt":"5","captain":false},{"carne":"47761","name":"JUAN IGNACIO POTRIE","shirt":"14","captain":false},{"carne":"45118","name":"LUCAS MARIA PEREIRA","shirt":"16","captain":false},{"carne":"48465","name":"NICOLAS KRUCHINSKI","shirt":"18","captain":false},{"carne":"46708","name":"AGUSTIN RAUL RODRIGUEZ","shirt":"21","captain":false},{"carne":"49606","name":"ALEJO MONTERROSO","shirt":"22","captain":false},{"carne":"48037","name":"MATEO FABREGAT","shirt":"24","captain":false},{"carne":"44291","name":"IGNACIO GEISINGER","shirt":"50","captain":true},{"carne":"46795","name":"BRUNO ABBATE","shirt":"83","captain":false}],"subs":[{"out_carne":"44291","out_name":"IGNACIO GEISINGER","in_carne":"47764","in_name":"BRUNO ZEFFERINO","shirt":"11","minute":"45"},{"out_carne":"49606","out_name":"ALEJO MONTERROSO","in_carne":"44908","in_name":"EDUARDO ARTAGAVEYTIA","shirt":"4","minute":"62"},{"out_carne":"48465","out_name":"NICOLAS KRUCHINSKI","in_carne":"44291","in_name":"IGNACIO GEISINGER","shirt":"50","minute":"76"}],"goals":[{"carne":"47597","name":"ISMAEL  FOPTIOS JAIDOPULOS","minute":"4","own_goal":true},{"carne":"44899","name":"JUAN MARTIN DEFFEMINIS","minute":"28","own_goal":false},{"carne":"46795","name":"BRUNO ABBATE","minute":"35","own_goal":false}],"yellows":[],"reds":[]}