{"match_id":"69854","starters":[{"carne":"52787","name":"IGNACIO SLINGER","shirt":"10","captain":false},{"carne":"52997","name":"FELIX MARTIN ALVAREZ","shirt":"15","captain":false},{"carne":"53647","name":"MATIAS PINTOS","shirt":"27","captain":false},{"carne":"53032","name":"FACUNDO AGUSTIN GOLOUBINTSEFF","shirt":"41","captain":false},{"carne":"53895","name":"IÑAKI ZUASNABAR","shirt":"46","captain":false},{"carne":"53359","name":"CARLOS FLEURQUIN","shirt":"48","captain":true},{"carne":"52459","name":"BRUNO TACCONE","shirt":"60","captain":false},{"carne":"53033","name":"SANTIAGO GEISINGER","shirt":"66","captain":false},{"carne":"52998","name":"MARCOS ALVAREZ","shirt":"68","captain":false},{"carne":"52784","name":"MATEO JOSE PONCE DE LEON","shirt":"82","captain":false},{"carne":"53228","name":"MATEO COUTO","shirt":"95","captain":false}],"subs":[{"out_carne":"52998","out_name":"MARCOS ALVAREZ","in_carne":"53649","in_name":"JUAN GENINAZZI","shirt":"22","minute":"0"},{"out_carne":"53895","out_name":"IÑAKI ZUASNABAR","in_carne":"53000","in_name":"FEDERICO NUÑEZ","shirt":"11","minute":"0"},{"out_carne":"53032","out_name":"FACUNDO AGUSTIN GOLOUBINTSEFF","in_carne":"54181","in_name":"AGUSTIN BURGHI","shirt":"18","minute":"0"},{"out_carne":"52784","out_name":"MATEO JOSE PONCE DE LEON","in_carne":"53360","in_name":"SANTIAGO JORCIN","shirt":"67","minute":"0"},{"out_carne":"52787","out_name":"IGNACIO SLINGER","in_carne":"52996","in_name":"JUAN DIEGO DOMINGUEZ","shirt":"72","minute":"0"},{"out_carne":"53647","out_name":"MATIAS PINTOS","in_carne":"54011","in_name":"ALFONSO PEREZ","shirt":"61","minute":"0"},{"out_carne":"53032","out_name":"FACUNDO AGUSTIN GOLOUBINTSEFF","in_carne":"53650","in_name":"RENZO SANTIN","shirt":"85","minute":"0"},{"out_carne":"52997","out_name":"FELIX MARTIN ALVAREZ","in_carne":"52783","in_name":"DAAN TOMAS ELBERSE","shirt":"75","minute":"0"},{"out_carne":"52459","out_name":"BRUNO TACCONE","in_carne":"53050","in_name":"MATEO BLANCO","shirt":"24","minute":"0"}],"goals":[{"carne":"53647","name":"MATIAS PINTOS","minute":"36","own_goal":false},{"carne":"52787","name":"IGNACIO SLINGER","minute":"62","own_goal":false},{"carne":"52787","name":"IGNACIO SLINGER","minute":"64","own_goal":false},{"carne":"53649","name":"JUAN GENINAZZI","minute":"71","own_goal":false}],"yellows":[{"name":"MATEO JOSE PONCE DE LEON"},{"name":"MATIAS PINTOS"}],"reds":[]}