{"match_id":"76678","starters":[{"carne":"28362","name":"JUAN PABLO MARSICANO","shirt":"1","captain":false},{"carne":"44809","name":"TOMAS JOSE SANZ","shirt":"6","captain":false},{"carne":"28371","name":"MAXIMILIANO JAVIER CRISTIANI","shirt":"9","captain":false},{"carne":"28619","name":"NICOLAS RODRIGUEZ","shirt":"11","captain":false},{"carne":"19944","name":"MAURICIO JAVIER GENINAZZI","shirt":"18","captain":false},{"carne":"43969","name":"MAURO DONNANGELO","shirt":"20","captain":false},{"carne":"29653","name":"MARTIN MUSETTI","shirt":"21","captain":false},{"carne":"44810","name":"SANTIAGO GONZALEZ","shirt":"24","captain":false},{"carne":"39903","name":"MANUEL FERNANDEZ","shirt":"25","captain":false},{"carne":"40246","name":"LUCAS NERY CALCAGNO","shirt":"65","captain":false},{"carne":"47764","name":"BRUNO ZEFFERINO","shirt":"77","captain":false}],"subs":[],"goals":[{"carne":"29653","name":"MARTIN MUSETTI","minute":"31","own_goal":false},{"carne":"28619","name":"NICOLAS RODRIGUEZ","minute":"95","own_goal":false}],"yellows":[],"reds":[]}