{"match_id":"79879","starters":[{"carne":"54770","name":"SANTINO SETTIN","shirt":"0","captain":false},{"carne":"56131","name":"SEBASTIAN OLAVE","shirt":"7","captain":false},{"carne":"55875","name":"AGUSTIN AGUIRRE","shirt":"17","captain":false},{"carne":"56876","name":"FACUNDO MIGNONE","shirt":"22","captain":false},{"carne":"56133","name":"FRANCO GAMBOGGI","shirt":"23","captain":false},{"carne":"56132","name":"SEBASTIAN VARGAS","shirt":"24","captain":false},{"carne":"56869","name":"NICOLAS PODESTA","shirt":"44","captain":false},{"carne":"55839","name":"FELIPE CONDORELLI","shirt":"45","captain":false},{"carne":"55182","name":"JUAN IGNACIO CABRERA","shirt":"47","captain":false},{"carne":"54773","name":"JUAN IGNACIO PODESTA","shirt":"59","captain":false},{"carne":"54767","name":"BAUTISTA PEREZ DEL CASTILLO","shirt":"79","captain":true}],"subs":[],"goals":[{"carne":"54770","name":"SANTINO SETTIN","minute":"44","own_goal":false},{"carne":"55182","name":"JUAN IGNACIO CABRERA","minute":"78","own_goal":false}],"yellows":[],"reds":[]}