{"match_id":"93126","starters":[{"carne":"64675","name":"LUCAS PUCCIARELLI","shirt":"1","captain":false},{"carne":"63921","name":"JOAQUIN ZUBILLAGA","shirt":"4","captain":false},{"carne":"63920","name":"FELIPE ZUBILLAGA","shirt":"5","captain":false},{"carne":"65710","name":"LUCIO AMEGLIO","shirt":"7","captain":false},{"carne":"65413","name":"ISIDORO ALBERTO JAIME","shirt":"8","captain":false},{"carne":"63919","name":"SANTINO AMAYA","shirt":"9","captain":true},{"carne":"64007","name":"LAUTARO FERNANDEZ","shirt":"10","captain":false},{"carne":"65712","name":"GUILLERMO PIEDRAFITA","shirt":"21","captain":false},{"carne":"64676","name":"PEDRO VECHIO","shirt":"26","captain":false},{"carne":"62864","name":"MILO ESTEVEZ","shirt":"36","captain":false},{"carne":"65411","name":"FRANCISCO IGLESIA","shirt":"40","captain":false}],"subs":[{"out_carne":"64675","out_name":"LUCAS PUCCIARELLI","in_carne":"65709","in_name":"ALFONSO MARIA FABINI","shirt":"12","minute":"45"}],"goals":[{"carne":"65710","name":"LUCIO AMEGLIO","minute":"34","own_goal":false},{"carne":"65710","name":"LUCIO AMEGLIO","minute":"55","own_goal":false},{"carne":"64676","name":"PEDRO VECHIO","minute":"57","own_goal":false},{"carne":"65710","name":"LUCIO AMEGLIO","minute":"65","own_goal":false},{"carne":"63919","name":"SANTINO AMAYA","minute":"72","own_goal":false}],"yellows":[],"reds":[]}